{
  "AK": {
    "name": "Alaska",
    "code": "AK",
    "dates": {
      "person": "2020-03-05",
      "online": "2020-03-05",
      "mail": "2020-03-05"
    }
  },
  "AL": {
    "name": "Alabama",
    "code": "AL",
    "dates": {
      "person": "2020-02-14",
      "online": "2020-02-17",
      "mail": "2020-02-17"
    }
  },
  "AR": {
    "name": "Arkansas",
    "code": "AR",
    "dates": {
      "person": "2020-02-04",
      "mail": "2020-02-04"
    }
  },
  "AZ": {
    "name": "Arizona",
    "code": "AZ",
    "dates": {
      "person": "2020-02-03",
      "mail": "2020-02-03"
    }
  },
  "CA": {
    "name": "California",
    "code": "CA",
    "dates": {
      "person": "2020-03-03",
      "online": "2020-02-17",
      "mail": "2020-02-17"
    }
  },
  "CO": {
    "name": "Colorado",
    "code": "CO",
    "dates": {
      "person": "2020-03-03",
      "online": "2020-02-24",
      "mail": "2020-02-24"
    }
  },
  "CT": {
    "name": "Connecticut",
    "code": "CT",
    "dates": {
      "person": "2020-04-27",
      "online": "2020-04-23",
      "mail": "2020-04-23"
    }
  },
  "DC": {
    "name": "District of Columbia",
    "code": "DC",
    "dates": {
      "person": "2020-06-02",
      "online": "2020-5-12",
      "mail": "2020-05-12"
    }
  }
}